manamodeller/__init__.py
manamodeller/batchs.py
manamodeller/dars.py
manamodeller/modelling.py
manamodeller/results_analysis.py
manamodeller/results_processing.py
manamodeller/utils.py
manamodeller-0.1.2.dist-info/METADATA
manamodeller-0.1.2.dist-info/WHEEL
manamodeller-0.1.2.dist-info/RECORD
