Metadata-Version: 2.1
Name: manamodeller
Version: 0.1.2
Summary: 
Author: Louison Fresnais
Author-email: fresnaislouison@gmail.com
Requires-Python: >=3.7,<3.10
Classifier: Programming Language :: Python :: 3
Classifier: Programming Language :: Python :: 3.7
Classifier: Programming Language :: Python :: 3.8
Classifier: Programming Language :: Python :: 3.9
Requires-Dist: dexom-python (>=1.0)
Requires-Dist: jproperties (>=2.1.1)
Requires-Dist: jupyterlab (>=4.0)
Requires-Dist: networkx (>=2.8.4)
Requires-Dist: numpy (>=1.2.0,<2.0.0)
Requires-Dist: pandas (<=1.5.0)
Requires-Dist: progressbar (>=2.5,<3.0)
Requires-Dist: pyvis (>=0.3.2)
Requires-Dist: tqdm (>=4.65.0,<5.0.0)
Requires-Dist: xlsxwriter (>=3.1.0)
